{
  "host": "",
  "errors": {
    "error.COMMON_ERROR": {
      "code": 1001500001,
      "message": "[COMMON_ERROR]通用错误: ",
      "data": null
    },
    "error.INTERNAL_ERROR": {
      "code": -1,
      "message": "[INTERNAL_ERROR]Internal Error: ",
      "data": null
    },
    "error.BAD_REQUEST": {
      "code": -2,
      "message": "[BAD_REQUEST]入参检测错误: ",
      "data": null
    },
    "error.NOT_FOUND": {
      "code": -3,
      "message": "[NOT_FOUND]not found: ",
      "data": null
    }
  },
  "apis": {
    "index": {
      "name": "index",
      "desc": "index",
      "group": "",
      "request": {
        "method": "get",
        "path": "",
        "query": {
          "name": {
            "_type": "string",
            "_default": "Robot Xiaolan",
            "_desc": "名字 ",
            "_length": [
              0,
              9007199254740991
            ]
          }
        },
        "params": {},
        "body": {}
      },
      "response": {
        "body": {
          "success": [
            {
              "code": {
                "_type": "number",
                "_assert": 200
              },
              "data": {
                "name": {
                  "_type": "string"
                }
              },
              "message": {
                "_type": "string"
              }
            }
          ],
          "failed": []
        }
      }
    }
  }
}